tshirt/__init__.py
tshirt/allk1255_centroid.py
tshirt/example_fits.py
tshirt/fit_models.py
tshirt/fit_tser_emcee.py
tshirt/mie_model.py
tshirt/quick_timeit.py
tshirt/specific_fits.py
tshirt/tser_tests.py
tshirt/chisquare/directory_placeholder.dat
tshirt/cleaned_tser/directory_placeholder.dat
tshirt/directory_info/directory_list.yaml
tshirt/directory_info/example_data_list.txt
tshirt/existing_dat/spectra/fratio_yang2016.csv
tshirt/parameters/fit_params.yaml
tshirt/parameters/telluric_bands.yaml
tshirt/parameters/mie_params/simplePoly.yaml
tshirt/parameters/phot_params/example_batch_phot.yaml
tshirt/parameters/phot_params/example_phot_parameters.yaml
tshirt/parameters/phot_params/keywords_for_phot_pipeline.csv
tshirt/parameters/phot_params/test_params/phot_param_k2_22_annulus.yaml
tshirt/parameters/phot_params/test_params/phot_param_k2_22_colrow.yaml
tshirt/parameters/phot_params/test_params/test_drifting_psf.yaml
tshirt/parameters/phot_params/test_params/test_rowamp_sub.yaml
tshirt/parameters/reduction_parameters/example_reduction_parameters.yaml
tshirt/parameters/spec_params/default_params.yaml
tshirt/parameters/spec_params/example_batch_spec_parameters.yaml
tshirt/parameters/spec_params/example_spec_parameters.yaml
tshirt/parameters/spec_params/test_params/basic_hst_spec.yaml
tshirt/pipeline/__init__.py
tshirt/pipeline/analysis.py
tshirt/pipeline/fit_2dgauss.py
tshirt/pipeline/phot_pipeline.py
tshirt/pipeline/prep_images.py
tshirt/pipeline/sim_data.py
tshirt/pipeline/spec_pipeline.py
tshirt/pipeline/utils.py
tshirt/pipeline/instrument_specific/__init__.py
tshirt/pipeline/instrument_specific/check_wavecal.py
tshirt/pipeline/instrument_specific/hst_inst_funcs.py
tshirt/pipeline/instrument_specific/jwst_inst_funcs.py
tshirt/pipeline/instrument_specific/rowamp_sub.py
tshirt/tests/test_phot_algorithms.py
tshirt/tests/test_pipe_basics.py
tshirt/tests/test_rowamp_sub.py
tshirt/tests/test_window_placement.py
tshirt-0.4.dist-info/LICENSE
tshirt-0.4.dist-info/METADATA
tshirt-0.4.dist-info/WHEEL
tshirt-0.4.dist-info/top_level.txt
tshirt-0.4.dist-info/RECORD
