Metadata-Version: 2.1
Name: tshirt
Version: 0.4
Summary: A package to analyze time series data, especially for exoplanets
Home-page: https://github.com/eas342/tshirt
Author: Everett Schlawin, Kayli Glidic
License-File: LICENSE
Requires-Dist: numpy >=1.15
Requires-Dist: scipy >=1.1.0
Requires-Dist: astropy >=2.0
Requires-Dist: tqdm >=4.46.0
Requires-Dist: photutils >=0.4.1
Requires-Dist: bokeh >=1.4.0
Requires-Dist: pytest
Requires-Dist: celerite2
